matchbox/__init__.py
matchbox/client/__init__.py
matchbox/client/_settings.py
matchbox/client/dags.py
matchbox/client/locations.py
matchbox/client/queries.py
matchbox/client/results.py
matchbox/client/sources.py
matchbox/client/_handler/__init__.py
matchbox/client/_handler/admin.py
matchbox/client/_handler/auth.py
matchbox/client/_handler/collections.py
matchbox/client/_handler/eval.py
matchbox/client/_handler/groups.py
matchbox/client/_handler/main.py
matchbox/client/_handler/query.py
matchbox/client/cli/__init__.py
matchbox/client/cli/admin.py
matchbox/client/cli/annotations.py
matchbox/client/cli/auth.py
matchbox/client/cli/collections.py
matchbox/client/cli/groups.py
matchbox/client/cli/main.py
matchbox/client/cli/eval/__init__.py
matchbox/client/cli/eval/app.py
matchbox/client/cli/eval/modals.py
matchbox/client/cli/eval/run.py
matchbox/client/cli/eval/styles.tcss
matchbox/client/cli/eval/widgets/__init__.py
matchbox/client/cli/eval/widgets/assignment.py
matchbox/client/cli/eval/widgets/styling.py
matchbox/client/cli/eval/widgets/table.py
matchbox/client/eval/__init__.py
matchbox/client/eval/samples.py
matchbox/client/models/__init__.py
matchbox/client/models/comparison.py
matchbox/client/models/models.py
matchbox/client/models/dedupers/__init__.py
matchbox/client/models/dedupers/base.py
matchbox/client/models/dedupers/naive.py
matchbox/client/models/linkers/__init__.py
matchbox/client/models/linkers/base.py
matchbox/client/models/linkers/deterministic.py
matchbox/client/models/linkers/splinklinker.py
matchbox/client/models/linkers/weighteddeterministic.py
matchbox/common/__init__.py
matchbox/common/arrow.py
matchbox/common/datatypes.py
matchbox/common/db.py
matchbox/common/dtos.py
matchbox/common/eval.py
matchbox/common/exceptions.py
matchbox/common/hash.py
matchbox/common/logging.py
matchbox/common/transform.py
matchbox/common/factories/__init__.py
matchbox/common/factories/dags.py
matchbox/common/factories/entities.py
matchbox/common/factories/models.py
matchbox_db-0.9.1.dist-info/licenses/LICENSE
matchbox_db-0.9.1.dist-info/METADATA
matchbox_db-0.9.1.dist-info/WHEEL
matchbox_db-0.9.1.dist-info/entry_points.txt
matchbox_db-0.9.1.dist-info/top_level.txt
matchbox_db-0.9.1.dist-info/RECORD
