Metadata-Version: 2.4
Name: matchbox-db
Version: 0.9.1
Summary: A framework for orchestrating and comparing data linking and deduplication methodologies.
Author: Department for Business and Trade
Project-URL: Documentation, https://uktrade.github.io/matchbox/
Project-URL: Repository, https://github.com/uktrade/matchbox.git
Requires-Python: <3.14,>=3.11
License-File: LICENSE
Requires-Dist: click>=8.1.7
Requires-Dist: cryptography>=44.0.2
Requires-Dist: duckdb>=1.1.1
Requires-Dist: email-validator>=2.3.0
Requires-Dist: faker>=36.1.1
Requires-Dist: frozendict>=2.4.6
Requires-Dist: httpx>=0.28.0
Requires-Dist: pandas<3,>=2.2.3
Requires-Dist: platformdirs>=4.5.0
Requires-Dist: polars-hash>=0.5.3
Requires-Dist: polars>=1.32.3
Requires-Dist: psutil>=7.1.3
Requires-Dist: psycopg[binary,pool]>=3.2.6
Requires-Dist: pyarrow>=17.0.0
Requires-Dist: pydantic-settings>=2.5.2
Requires-Dist: pydantic>=2.9.2
Requires-Dist: rich>=13.9.4
Requires-Dist: rustworkx>=0.15.1
Requires-Dist: splink<4.1.0,>=4.0.5
Requires-Dist: sqlalchemy>=2.0.35
Requires-Dist: sqlglot[rs]>=26.12.1
Requires-Dist: tenacity>=9.1.2
Requires-Dist: textual>=0.87.1
Requires-Dist: typer>=0.15.0
Provides-Extra: server
Requires-Dist: adbc-driver-postgresql>=1.5.0; extra == "server"
Requires-Dist: alembic>=1.15.2; extra == "server"
Requires-Dist: boto3>=1.35.99; extra == "server"
Requires-Dist: celery[redis]>=5.5.3; extra == "server"
Requires-Dist: fastapi[standard-no-fastapi-cloud-cli]>=0.116.0; extra == "server"
Requires-Dist: python-multipart>=0.0.18; extra == "server"
Requires-Dist: redis>=5.2.1; extra == "server"
Requires-Dist: tomli>=2.0.1; extra == "server"
Dynamic: license-file
